cases/__init__.py
cases/ha/__init__.py
cases/ha/test_ha.py
cases/ha/test_ha_HA.robot
cases/login/__init__.py
cases/login/login_1.py
cases/login/login_1.robot
pyrobot/__init__.py
pyrobot/case.py
pyrobot/core.py
pyrobot/exceptions.py
pyrobot/log.py
pyrobot/run.py
pyrobotf-1.0.0.dist-info/LICENSE
pyrobotf-1.0.0.dist-info/METADATA
pyrobotf-1.0.0.dist-info/WHEEL
pyrobotf-1.0.0.dist-info/top_level.txt
pyrobotf-1.0.0.dist-info/RECORD
