Metadata-Version: 2.1
Name: pyrobotf
Version: 1.0.0
Summary: A test framework based on robot.
Home-page: https://github.com/txu2k8/pyrobot
Author: tao.xu
Author-email: tao.xu2008@outlook.com
License: MIT
Keywords: python,unittest,robot
Platform: UNKNOWN
Classifier: Intended Audience :: Developers
Classifier: License :: OSI Approved :: MIT License
Classifier: Natural Language :: English
Classifier: Programming Language :: Python :: 3
Requires-Python: >=3.4.0
Requires-Dist: coloredlogs (==14.0)
Requires-Dist: humanfriendly (==9.0)
Requires-Dist: prettytable (==2.0.0)
Requires-Dist: pyreadline (==2.1)
Requires-Dist: robotframework (==3.2.2)
Requires-Dist: wcwidth (==0.2.5)
